pytest_hoverfly_wrapper/__init__.py
pytest_hoverfly_wrapper/block_domain_template.json
pytest_hoverfly_wrapper/download.py
pytest_hoverfly_wrapper/logger.py
pytest_hoverfly_wrapper/plugin.py
pytest_hoverfly_wrapper/simulations.py
pytest_hoverfly_wrapper-1.0.1.dist-info/LICENSE
pytest_hoverfly_wrapper-1.0.1.dist-info/METADATA
pytest_hoverfly_wrapper-1.0.1.dist-info/WHEEL
pytest_hoverfly_wrapper-1.0.1.dist-info/entry_points.txt
pytest_hoverfly_wrapper-1.0.1.dist-info/top_level.txt
pytest_hoverfly_wrapper-1.0.1.dist-info/RECORD
