Metadata-Version: 2.1
Name: pytest-hoverfly-wrapper
Version: 1.0.1
Summary: Integrates the Hoverfly HTTP proxy into Pytest
Home-page: https://github.com/kopernio/pytest-hoverfly-wrapper
Author: Veli Akiner
Author-email: veli.akiner@gmail.com
Maintainer: Veli Akiner
Maintainer-email: veli.akiner@gmail.com
License: MIT
Classifier: Development Status :: 5 - Production/Stable
Classifier: Framework :: Pytest
Classifier: Intended Audience :: Developers
Classifier: Topic :: Software Development :: Testing
Classifier: Programming Language :: Python
Classifier: Programming Language :: Python :: 3
Classifier: Programming Language :: Python :: 3.7
Classifier: Programming Language :: Python :: 3.8
Classifier: Programming Language :: Python :: 3.10
Classifier: Programming Language :: Python :: 3.11
Classifier: Programming Language :: Python :: Implementation :: CPython
Classifier: Programming Language :: Python :: Implementation :: PyPy
Classifier: Operating System :: Microsoft :: Windows
Classifier: Operating System :: POSIX :: Linux
Classifier: Operating System :: MacOS
Classifier: License :: OSI Approved :: MIT License
Requires-Python: >=3.7
License-File: LICENSE
Requires-Dist: pytest (>=3.7.0)
Requires-Dist: requests
Requires-Dist: python-dateutil
Requires-Dist: polling
Requires-Dist: requests-cache (==0.9.8)
